embdata/__init__.py
embdata/concurrency.py
embdata/coordinate.py
embdata/describe.py
embdata/episode.py
embdata/features.py
embdata/geometry.py
embdata/list.py
embdata/ndarray.py
embdata/requirements.txt
embdata/sample.py
embdata/setup.sh
embdata/supervision.py
embdata/time.py
embdata/trajectory.py
embdata/units.py
embdata/_internal/__init__.py
embdata/_internal/_config.py
embdata/_internal/_core_metadata.py
embdata/_internal/_core_utils.py
embdata/_internal/_dataclasses.py
embdata/_internal/_decorators.py
embdata/_internal/_decorators_v1.py
embdata/_internal/_discriminated_union.py
embdata/_internal/_docs_extraction.py
embdata/_internal/_fields.py
embdata/_internal/_forward_ref.py
embdata/_internal/_generate_schema.py
embdata/_internal/_generics.py
embdata/_internal/_git.py
embdata/_internal/_internal_dataclass.py
embdata/_internal/_known_annotated_metadata.py
embdata/_internal/_mock_val_ser.py
embdata/_internal/_model_construction.py
embdata/_internal/_repr.py
embdata/_internal/_sample.py
embdata/_internal/_schema_generation_shared.py
embdata/_internal/_signature.py
embdata/_internal/_state.py
embdata/_internal/_std_types_schema.py
embdata/_internal/_typing_extra.py
embdata/_internal/_utils.py
embdata/_internal/_validate_call.py
embdata/_internal/_validators.py
embdata/_internal/model_construction.py
embdata/_typing/__init__.py
embdata/_typing/_add_docstring.py
embdata/_typing/_array_like.py
embdata/_typing/_callable.pyi
embdata/_typing/_char_codes.py
embdata/_typing/_dtype_like.py
embdata/_typing/_extended_precision.py
embdata/_typing/_nbit.py
embdata/_typing/_nested_sequence.py
embdata/_typing/_scalars.py
embdata/_typing/_shape.py
embdata/_typing/_ufunc.pyi
embdata/_typing/setup.py
embdata/language/__init__.py
embdata/language/describe_geometry.py
embdata/motion/__init__.py
embdata/motion/control.py
embdata/motion/motion.py
embdata/resources/color_image.png
embdata/resources/current_image.png
embdata/resources/depth_anything_gray.png
embdata-0.0.13.dist-info/METADATA
embdata-0.0.13.dist-info/WHEEL
embdata-0.0.13.dist-info/licenses/LICENSE.txt
embdata-0.0.13.dist-info/RECORD
