Metadata-Version: 2.3
Name: embdata
Version: 0.0.13
Summary: Data, types, pipes, manipulation for embodied learning.
Author-email: mbodi ai team <info@mbodi.ai>
License-Expression: Apache-2.0
License-File: LICENSE.txt
Classifier: Development Status :: 4 - Beta
Classifier: Programming Language :: Python
Classifier: Programming Language :: Python :: 3.10
Classifier: Programming Language :: Python :: 3.11
Classifier: Programming Language :: Python :: 3.12
Classifier: Programming Language :: Python :: Implementation :: CPython
Classifier: Programming Language :: Python :: Implementation :: PyPy
Requires-Python: >=3.10
Requires-Dist: aiocache
Requires-Dist: compress-pickle
Requires-Dist: datasets
Requires-Dist: datasets==2.20.0
Requires-Dist: embdata
Requires-Dist: funkify
Requires-Dist: gymnasium==0.29.1
Requires-Dist: lager
Requires-Dist: methodtools==0.4.7
Requires-Dist: numpy==1.26.4
Requires-Dist: opencv-python
Requires-Dist: pillow
Requires-Dist: plotext==5.2.8
Requires-Dist: pydantic-settings
Requires-Dist: pydantic==2.7.4
Requires-Dist: requires
Requires-Dist: rich==13.7.1
Requires-Dist: scikit-learn
Provides-Extra: 3d
Requires-Dist: open3d; extra == '3d'
Provides-Extra: all
Requires-Dist: datasets==2.20.0; extra == 'all'
Requires-Dist: einops==0.8.0; extra == 'all'
Requires-Dist: ffpyplayer; extra == 'all'
Requires-Dist: matplotlib; extra == 'all'
Requires-Dist: opencv-python; extra == 'all'
Requires-Dist: plotext==5.2.8; extra == 'all'
Requires-Dist: pyaudio; extra == 'all'
Requires-Dist: rerun-sdk==0.17.0; extra == 'all'
Requires-Dist: shapely==2.0.4; extra == 'all'
Requires-Dist: torch==2.3.1; extra == 'all'
Requires-Dist: torchvision==0.18.1; extra == 'all'
Requires-Dist: transformers>=4.42.4; extra == 'all'
Provides-Extra: audio
Requires-Dist: pyaudio; extra == 'audio'
Provides-Extra: mpl
Requires-Dist: matplotlib; extra == 'mpl'
Provides-Extra: plot
Requires-Dist: plotext==5.2.8; extra == 'plot'
Provides-Extra: stream
Requires-Dist: opencv-python; extra == 'stream'
